exactitude/__init__.py
exactitude/address.py
exactitude/common.py
exactitude/country.py
exactitude/date.py
exactitude/domain.py
exactitude/email.py
exactitude/iban.py
exactitude/identifier.py
exactitude/ip.py
exactitude/language.py
exactitude/name.py
exactitude/phone.py
exactitude/url.py
exactitude-2.3.3.dist-info/DESCRIPTION.rst
exactitude-2.3.3.dist-info/METADATA
exactitude-2.3.3.dist-info/RECORD
exactitude-2.3.3.dist-info/WHEEL
exactitude-2.3.3.dist-info/metadata.json
exactitude-2.3.3.dist-info/namespace_packages.txt
exactitude-2.3.3.dist-info/top_level.txt
tests/__init__.py
tests/test_addresses.py
tests/test_countries.py
tests/test_dates.py
tests/test_domains.py
tests/test_emails.py
tests/test_iban.py
tests/test_identifiers.py
tests/test_ip.py
tests/test_languages.py
tests/test_names.py
tests/test_phones.py
tests/test_urls.py
