Metadata-Version: 2.0
Name: exactitude
Version: 2.3.3
Summary: A library with real-world data parsers.
Home-page: http://github.com/alephdata/dalet
Author: Friedrich Lindenberg
Author-email: friedrich@pudo.org
License: MIT
Keywords: names countries phones domains email country
Platform: UNKNOWN
Classifier: Development Status :: 3 - Alpha
Classifier: Intended Audience :: Developers
Classifier: License :: OSI Approved :: MIT License
Classifier: Operating System :: OS Independent
Classifier: Programming Language :: Python :: 2.7
Classifier: Programming Language :: Python :: 3.3
Classifier: Programming Language :: Python :: 3.6
Requires-Dist: six (>=1.11.0)
Requires-Dist: normality (>=0.5.6)
Requires-Dist: pytz (>=2017.3)
Requires-Dist: babel (>=2.5.1)
Requires-Dist: urlnormalizer (>=1.0.3)
Requires-Dist: countrynames (>=1.2)
Requires-Dist: parsedatetime (>=2.1)
Requires-Dist: python-dateutil (>=2.6.1)
Requires-Dist: phonenumbers (>=8.8.4)
Requires-Dist: python-stdnum (>=1.8)
